__init__.py
warborne.py
warborne-1.0.0.dist-info/licenses/LICENSE
warborne-1.0.0.dist-info/METADATA
warborne-1.0.0.dist-info/WHEEL
warborne-1.0.0.dist-info/top_level.txt
warborne-1.0.0.dist-info/RECORD
