Metadata-Version: 2.4
Name: warborne
Version: 1.0.0
Summary: A simple hashing library based on vowel counting
Author-email: AkiTheMemeGod <k.akashkumar@gmail.com>
Project-URL: Homepage, https://github.com/AkiTheMemeGod/Warborne_pypi_package
Project-URL: Bug Tracker, https://github.com/AkiTheMemeGod/Warborne_pypi_package/issues
Classifier: Programming Language :: Python :: 3
Classifier: License :: OSI Approved :: MIT License
Classifier: Operating System :: OS Independent
Requires-Python: >=3.7
License-File: LICENSE
Dynamic: license-file
